Makefile
README.rst
requirements.txt
setup.cfg
setup.py
watchdog.ini
briefkasten_watchdog/__init__.py
briefkasten_watchdog.egg-info/PKG-INFO
briefkasten_watchdog.egg-info/SOURCES.txt
briefkasten_watchdog.egg-info/dependency_links.txt
briefkasten_watchdog.egg-info/entry_points.txt
briefkasten_watchdog.egg-info/not-zip-safe
briefkasten_watchdog.egg-info/requires.txt
briefkasten_watchdog.egg-info/top_level.txt